fokker_planck/__init__.py
fokker_planck/base.py
fokker_planck/containers.py
fokker_planck/forceFunctions.py
fokker_planck/integrator.py
fokker_planck/integrator_2D.py
fokker_planck/simulator/__init__.py
fokker_planck/simulator/base.py
fokker_planck/simulator/simulator.py
fokker_planck/types/__init__.py
fokker_planck/types/basetypes.py
fokker_planck/util/__init__.py
fokker_planck/util/notebooks.py
fokker_planck/visualizations/__init__.py
fokker_planck/visualizations/examples.py
fokker_planck-1.0.17.dist-info/LICENSE
fokker_planck-1.0.17.dist-info/METADATA
fokker_planck-1.0.17.dist-info/WHEEL
fokker_planck-1.0.17.dist-info/top_level.txt
fokker_planck-1.0.17.dist-info/RECORD
