Metadata-Version: 2.1
Name: fokker-planck
Version: 1.0.17
Summary: A Fokker-Planck integrator in python
Author: Steven Large
Author-email: stevelarge7@gmail.com
License: MIT
Project-URL: Source, https://github.com/StevenJLarge/FokkerPlanck
Classifier: Development Status :: 3 - Alpha
Classifier: Intended Audience :: Science/Research
Classifier: License :: OSI Approved :: MIT License
Classifier: Programming Language :: Python
Classifier: Topic :: Scientific/Engineering :: Physics
Classifier: Topic :: Scientific/Engineering :: Mathematics
License-File: LICENSE
Requires-Dist: matplotlib
Requires-Dist: numpy
Requires-Dist: scipy
Requires-Dist: statsmodels
